icestream/__init__.py
icestream/__main__.py
icestream/errors.py
icestream/logger.py
icestream/utils.py
icestream/admin/__init__.py
icestream/alembic/README
icestream/alembic/env.py
icestream/alembic/script.py.mako
icestream/alembic/versions/298875b23096_remove_unnecessary_compaction_columns_.py
icestream/alembic/versions/5cc5497d09b5_add_byte_start_end_to_walfileoffset.py
icestream/alembic/versions/9f0f8ebe3914_add_min_max_timestamps.py
icestream/alembic/versions/bf37d72775bc_initial_schema.py
icestream/alembic/versions/c354df1a9089_add_log_start_offset_to_partition.py
icestream/alembic/versions/d77fb56536a8_use_partition_topic_name_and_number_in_.py
icestream/compaction/__init__.py
icestream/compaction/parquet_compactor.py
icestream/compaction/schema.py
icestream/compaction/types.py
icestream/compaction/wal_to_parquet.py
icestream/config/__init__.py
icestream/db/__init__.py
icestream/kafkaserver/__init__.py
icestream/kafkaserver/handler.py
icestream/kafkaserver/metadata.py
icestream/kafkaserver/server.py
icestream/kafkaserver/types.py
icestream/kafkaserver/utils.py
icestream/kafkaserver/handlers/__init__.py
icestream/kafkaserver/handlers/add_offsets_to_txn.py
icestream/kafkaserver/handlers/add_partitions_to_txn.py
icestream/kafkaserver/handlers/add_raft_voter.py
icestream/kafkaserver/handlers/allocate_producer_ids.py
icestream/kafkaserver/handlers/alter_client_quotas.py
icestream/kafkaserver/handlers/alter_configs.py
icestream/kafkaserver/handlers/alter_partition.py
icestream/kafkaserver/handlers/alter_partition_reassignments.py
icestream/kafkaserver/handlers/alter_replica_log_dirs.py
icestream/kafkaserver/handlers/alter_user_scram_credentials.py
icestream/kafkaserver/handlers/api_versions.py
icestream/kafkaserver/handlers/assign_replicas_to_dirs.py
icestream/kafkaserver/handlers/begin_quorum_epoch.py
icestream/kafkaserver/handlers/broker_heartbeat.py
icestream/kafkaserver/handlers/broker_registration.py
icestream/kafkaserver/handlers/consumer_group_describe.py
icestream-0.1.6.dist-info/METADATA
icestream-0.1.6.dist-info/WHEEL
icestream-0.1.6.dist-info/entry_points.txt
icestream-0.1.6.dist-info/top_level.txt
icestream-0.1.6.dist-info/RECORD
