Metadata-Version: 2.4
Name: icestream
Version: 0.1.6
Summary: Add your description here
Requires-Python: >=3.13
Requires-Dist: aiosqlite>=0.21.0
Requires-Dist: alembic>=1.16.0
Requires-Dist: asyncpg>=0.30.0
Requires-Dist: boto3>=1.39.0
Requires-Dist: fastapi>=0.116.0
Requires-Dist: google-crc32c>=1.7.1
Requires-Dist: httpx>=0.28.0
Requires-Dist: hypercorn>=0.17.0
Requires-Dist: kio>=0.4.0
Requires-Dist: obstore>=0.7.0
Requires-Dist: pyarrow>=21.0.0
Requires-Dist: pydantic>=2.11.0
Requires-Dist: pyiceberg[rest-sigv4,s3fs]>=0.9.0
Requires-Dist: sqlalchemy>=2.0.0
Requires-Dist: structlog>=25.2.0
Provides-Extra: dev
Requires-Dist: aiokafka>=0.12.0; extra == "dev"
Requires-Dist: pytest>=8.4.0; extra == "dev"
Requires-Dist: pytest-asyncio>=1.0.0; extra == "dev"
